main.py
source_workday_raas/__init__.py
source_workday_raas/manifest.yaml
source_workday_raas/run.py
source_workday_raas/source.py
airbyte_source_workday_raas-0.1.0.dev202408051803.dist-info/METADATA
airbyte_source_workday_raas-0.1.0.dev202408051803.dist-info/WHEEL
airbyte_source_workday_raas-0.1.0.dev202408051803.dist-info/entry_points.txt
airbyte_source_workday_raas-0.1.0.dev202408051803.dist-info/RECORD
